setup.py
mifrie_dsnd_prob/Binomialdistribution.py
mifrie_dsnd_prob/Gaussiandistribution.py
mifrie_dsnd_prob/Generaldistribution.py
mifrie_dsnd_prob/__init__.py
mifrie_dsnd_prob.egg-info/PKG-INFO
mifrie_dsnd_prob.egg-info/SOURCES.txt
mifrie_dsnd_prob.egg-info/dependency_links.txt
mifrie_dsnd_prob.egg-info/not-zip-safe
mifrie_dsnd_prob.egg-info/top_level.txt