Metadata-Version: 1.0
Name: mifrie-dsnd-prob
Version: 0.2
Summary: Gaussian and binomial distributions
Home-page: UNKNOWN
Author: UNKNOWN
Author-email: UNKNOWN
License: UNKNOWN
Platform: UNKNOWN
